{
  "per_subject_score": {
    "Python": 0.0,
    "EDA": 0.0,
    "SQL": 0.0,
    "POWER BI": 0.0,
    "Statistics": 0.0
  },
  "total_score": 0.0,
  "per_question": {
    "1": {
      "selected": null,
      "correct": null
    },
    "2": {
      "selected": null,
      "correct": null
    },
    "3": {
      "selected": null,
      "correct": null
    },
    "4": {
      "selected": null,
      "correct": null
    },
    "5": {
      "selected": null,
      "correct": null
    },
    "6": {
      "selected": null,
      "correct": null
    },
    "7": {
      "selected": null,
      "correct": null
    },
    "8": {
      "selected": null,
      "correct": null
    },
    "9": {
      "selected": null,
      "correct": null
    },
    "10": {
      "selected": null,
      "correct": null
    },
    "11": {
      "selected": null,
      "correct": null
    },
    "12": {
      "selected": null,
      "correct": null
    },
    "13": {
      "selected": null,
      "correct": null
    },
    "14": {
      "selected": null,
      "correct": null
    },
    "15": {
      "selected": null,
      "correct": null
    },
    "16": {
      "selected": null,
      "correct": null
    },
    "17": {
      "selected": null,
      "correct": null
    },
    "18": {
      "selected": null,
      "correct": null
    },
    "19": {
      "selected": null,
      "correct": null
    },
    "20": {
      "selected": null,
      "correct": null
    },
    "21": {
      "selected": null,
      "correct": null
    },
    "22": {
      "selected": null,
      "correct": null
    },
    "23": {
      "selected": null,
      "correct": null
    },
    "24": {
      "selected": null,
      "correct": null
    },
    "25": {
      "selected": null,
      "correct": null
    },
    "26": {
      "selected": null,
      "correct": null
    },
    "27": {
      "selected": null,
      "correct": null
    },
    "28": {
      "selected": null,
      "correct": null
    },
    "29": {
      "selected": null,
      "correct": null
    },
    "30": {
      "selected": null,
      "correct": null
    },
    "31": {
      "selected": null,
      "correct": null
    },
    "32": {
      "selected": null,
      "correct": null
    },
    "33": {
      "selected": null,
      "correct": null
    },
    "34": {
      "selected": null,
      "correct": null
    },
    "35": {
      "selected": null,
      "correct": null
    },
    "36": {
      "selected": null,
      "correct": null
    },
    "37": {
      "selected": null,
      "correct": null
    },
    "38": {
      "selected": null,
      "correct": null
    },
    "39": {
      "selected": null,
      "correct": null
    },
    "40": {
      "selected": null,
      "correct": null
    },
    "41": {
      "selected": null,
      "correct": null
    },
    "42": {
      "selected": null,
      "correct": null
    },
    "43": {
      "selected": null,
      "correct": null
    },
    "44": {
      "selected": null,
      "correct": null
    },
    "45": {
      "selected": null,
      "correct": null
    },
    "46": {
      "selected": null,
      "correct": null
    },
    "47": {
      "selected": null,
      "correct": null
    },
    "48": {
      "selected": null,
      "correct": null
    },
    "49": {
      "selected": null,
      "correct": null
    },
    "50": {
      "selected": null,
      "correct": null
    },
    "51": {
      "selected": null,
      "correct": null
    },
    "52": {
      "selected": null,
      "correct": null
    },
    "53": {
      "selected": null,
      "correct": null
    },
    "54": {
      "selected": null,
      "correct": null
    },
    "55": {
      "selected": null,
      "correct": null
    },
    "56": {
      "selected": null,
      "correct": null
    },
    "57": {
      "selected": null,
      "correct": null
    },
    "58": {
      "selected": null,
      "correct": null
    },
    "59": {
      "selected": null,
      "correct": null
    },
    "60": {
      "selected": null,
      "correct": null
    },
    "61": {
      "selected": null,
      "correct": null
    },
    "62": {
      "selected": null,
      "correct": null
    },
    "63": {
      "selected": null,
      "correct": null
    },
    "64": {
      "selected": null,
      "correct": null
    },
    "65": {
      "selected": null,
      "correct": null
    },
    "66": {
      "selected": null,
      "correct": null
    },
    "67": {
      "selected": null,
      "correct": null
    },
    "68": {
      "selected": null,
      "correct": null
    },
    "69": {
      "selected": null,
      "correct": null
    },
    "70": {
      "selected": null,
      "correct": null
    },
    "71": {
      "selected": null,
      "correct": null
    },
    "72": {
      "selected": null,
      "correct": null
    },
    "73": {
      "selected": null,
      "correct": null
    },
    "74": {
      "selected": null,
      "correct": null
    },
    "75": {
      "selected": null,
      "correct": null
    },
    "76": {
      "selected": null,
      "correct": null
    },
    "77": {
      "selected": null,
      "correct": null
    },
    "78": {
      "selected": null,
      "correct": null
    },
    "79": {
      "selected": null,
      "correct": null
    },
    "80": {
      "selected": null,
      "correct": null
    },
    "81": {
      "selected": null,
      "correct": null
    },
    "82": {
      "selected": null,
      "correct": null
    },
    "83": {
      "selected": null,
      "correct": null
    },
    "84": {
      "selected": null,
      "correct": null
    },
    "85": {
      "selected": null,
      "correct": null
    },
    "86": {
      "selected": null,
      "correct": null
    },
    "87": {
      "selected": null,
      "correct": null
    },
    "88": {
      "selected": null,
      "correct": null
    },
    "89": {
      "selected": null,
      "correct": null
    },
    "90": {
      "selected": null,
      "correct": null
    },
    "91": {
      "selected": null,
      "correct": null
    },
    "92": {
      "selected": null,
      "correct": null
    },
    "93": {
      "selected": null,
      "correct": null
    },
    "94": {
      "selected": null,
      "correct": null
    },
    "95": {
      "selected": null,
      "correct": null
    },
    "96": {
      "selected": null,
      "correct": null
    },
    "97": {
      "selected": null,
      "correct": null
    },
    "98": {
      "selected": null,
      "correct": null
    },
    "99": {
      "selected": null,
      "correct": null
    },
    "100": {
      "selected": null,
      "correct": null
    }
  },
  "ambiguous_count": 24,
  "template_used": "v1"
}